{"frameRate":24,"isGlobal":0,"armature":[{"defaultActions":[{"gotoAndPlay":"walk"}],"animation":[{"ffd":[],"frame":[],"slot":[],"duration":40,"bone":[{"frame":[{"transform":{},"duration":10,"curve":[0.5,0,0.5,1]},{"transform":{"y":2.1},"duration":10,"curve":[0.5,0,0.5,1]},{"transform":{},"duration":10,"curve":[0.5,0,0.5,1]},{"transform":{"y":2.1},"duration":10,"curve":[0.5,0,0.5,1]},{"tweenEasing":null,"transform":{},"duration":0}],"name":"root"},{"frame":[{"transform":{},"duration":20,"curve":[0.5,0,0.5,1]},{"transform":{"skX":44.8296,"skY":44.8296},"duration":20,"curve":[0.5,0,0.5,1]},{"tweenEasing":null,"transform":{},"duration":0}],"name":"armRight"},{"frame":[{"transform":{},"duration":20,"curve":[0.5,0,0.5,1]},{"transform":{},"duration":20,"curve":[0.5,0,0.5,1]},{"tweenEasing":null,"transform":{},"duration":0}],"name":"handRight"},{"frame":[{"transform":{},"duration":10,"curve":[0.5,0,0.5,1]},{"transform":{"skX":-36.5959,"skY":-36.5959},"duration":3,"curve":[0.5,0,0.5,1]},{"transform":{"skX":31.8587,"skY":31.8587},"duration":7,"curve":[0.5,0,0.5,1]},{"transform":{},"duration":10,"curve":[0.5,0,0.5,1]},{"transform":{"skX":-36.5959,"skY":-36.5959},"duration":3,"curve":[0.5,0,0.5,1]},{"transform":{"skX":31.8587,"skY":31.8587},"duration":7,"curve":[0.5,0,0.5,1]},{"tweenEasing":null,"transform":{},"duration":0}],"name":"clawRight"},{"frame":[{"transform":{},"duration":20,"curve":[0.5,0,0.5,1]},{"transform":{"skX":-15.2357,"skY":-15.2357},"duration":20,"curve":[0.5,0,0.5,1]},{"tweenEasing":null,"transform":{},"duration":0}],"name":"armLeft"},{"frame":[{"transform":{},"duration":20,"curve":[0.5,0,0.5,1]},{"transform":{},"duration":20,"curve":[0.5,0,0.5,1]},{"tweenEasing":null,"transform":{},"duration":0}],"name":"handLeft"},{"frame":[{"transform":{"skX":-25.2229,"skY":-25.2229},"duration":10,"curve":[0.5,0,0.5,1]},{"tweenEasing":0,"transform":{"skX":32.6289,"skY":32.6289},"duration":10},{"transform":{"skX":-24.6522,"skY":-24.6522},"duration":10,"curve":[0.5,0,0.5,1]},{"tweenEasing":0,"transform":{"skX":32.6289,"skY":32.6289},"duration":10},{"tweenEasing":null,"transform":{},"duration":0}],"name":"clawLeft"},{"frame":[{"transform":{},"duration":20,"curve":[0.5,0,0.5,1]},{"transform":{"skX":-26.6369,"skY":-26.6369},"duration":20,"curve":[0.5,0,0.5,1]},{"tweenEasing":null,"transform":{},"duration":0}],"name":"eyeLeft"},{"frame":[{"transform":{},"duration":20,"curve":[0.5,0,0.5,1]},{"transform":{"skX":35.3967,"skY":35.3967},"duration":20,"curve":[0.5,0,0.5,1]},{"tweenEasing":null,"transform":{},"duration":0}],"name":"eyeRight"},{"frame":[{"transform":{},"duration":10,"curve":[0.5,0,0.5,1]},{"transform":{"skX":41.2786,"skY":41.2786},"duration":10,"curve":[0.5,0,0.5,1]},{"transform":{},"duration":10,"curve":[0.5,0,0.5,1]},{"transform":{"skX":41.2786,"skY":41.2786},"duration":10,"curve":[0.5,0,0.5,1]},{"tweenEasing":null,"transform":{},"duration":0}],"name":"leg1"},{"frame":[{"transform":{},"duration":10,"curve":[0.5,0,0.5,1]},{"transform":{"skX":-19.0136,"skY":-19.0136},"duration":10,"curve":[0.5,0,0.5,1]},{"transform":{},"duration":10,"curve":[0.5,0,0.5,1]},{"transform":{"skX":-19.0136,"skY":-19.0136},"duration":10,"curve":[0.5,0,0.5,1]},{"tweenEasing":null,"transform":{},"duration":0}],"name":"leg2"},{"frame":[{"transform":{},"duration":10,"curve":[0.5,0,0.5,1]},{"transform":{"skX":28.9739,"skY":28.9739},"duration":10,"curve":[0.5,0,0.5,1]},{"transform":{},"duration":10,"curve":[0.5,0,0.5,1]},{"transform":{"skX":28.9739,"skY":28.9739},"duration":10,"curve":[0.5,0,0.5,1]},{"tweenEasing":null,"transform":{},"duration":0}],"name":"leg3"},{"frame":[{"transform":{},"duration":10,"curve":[0.5,0,0.5,1]},{"transform":{"skX":-33.7387,"skY":-33.7387},"duration":10,"curve":[0.5,0,0.5,1]},{"transform":{},"duration":10,"curve":[0.5,0,0.5,1]},{"transform":{"skX":-33.7387,"skY":-33.7387},"duration":10,"curve":[0.5,0,0.5,1]},{"tweenEasing":null,"transform":{},"duration":0}],"name":"leg4"}],"playTimes":0,"name":"walk"}],"skin":[{"name":"","slot":[{"display":[{"type":"image","name":"eyeLeft","transform":{"skX":90,"y":-0.75,"skY":90,"x":12.45}}],"name":"eyeLeft"},{"display":[{"type":"image","name":"leg1","transform":{"skX":-121.6075,"y":-0.22601999999999997,"skY":-121.6075,"x":10.956900000000001}}],"name":"leg1"},{"display":[{"type":"image","name":"clawRight","transform":{"skX":104.6764,"y":-1.14357,"skY":104.6764,"x":11.61882}}],"name":"clawRight"},{"display":[{"type":"image","name":"leg3","transform":{"skX":-45,"skY":-45,"x":9.9702}}],"name":"leg3"},{"display":[{"type":"image","name":"eyeRight","transform":{"skX":82.4879,"y":1.63584,"skY":82.4879,"x":13.983870000000001}}],"name":"eyeRight"},{"display":[{"type":"image","name":"armLeft","transform":{"skX":122.8285,"y":-0.61395,"skY":122.8285,"x":15.92634}}],"name":"armLeft"},{"display":[{"type":"image","name":"handRight","transform":{"skX":68.471,"y":-0.39683999999999997,"skY":68.471,"x":16.12971}}],"name":"handRight"},{"display":[{"type":"image","name":"clawLeft","transform":{"skX":73.1786,"y":-0.6144,"skY":73.1786,"x":11.880539999999998}}],"name":"clawLeft"},{"display":[{"type":"image","name":"leg2","transform":{"skX":-140.9061,"y":-0.8513099999999999,"skY":-140.9061,"x":8.22924}}],"name":"leg2"},{"display":[{"type":"image","name":"body","transform":{}}],"name":"body"},{"display":[{"type":"image","name":"leg4","transform":{"skX":-55.5816,"y":0.16269,"skY":-55.5816,"x":9.52569}}],"name":"leg4"},{"display":[{"type":"image","name":"handLeft","transform":{"skX":110.1196,"y":-0.8729699999999999,"skY":110.1196,"x":15.495899999999999}}],"name":"handLeft"},{"display":[{"type":"image","name":"armRight","transform":{"skX":54.3955,"y":0.67905,"skY":54.3955,"x":15.798869999999999}}],"name":"armRight"}]}],"type":"Armature","frameRate":24,"bone":[{"name":"root","transform":{"y":9.56523}},{"length":33,"transform":{"skX":-122.8285,"y":-9,"skY":-122.8285,"x":-21.599999999999998},"parent":"root","name":"armLeft"},{"length":25.2,"transform":{"skX":-90,"y":-21.9,"skY":-90,"x":-10.799999999999999},"parent":"root","name":"eyeLeft"},{"length":22.8,"transform":{"skX":121.6075,"y":9.9,"skY":121.6075,"x":-30.299999999999997},"parent":"root","name":"leg1"},{"length":29.7,"transform":{"skX":-54.3955,"y":-7.8,"skY":-54.3955,"x":23.099999999999998},"parent":"root","name":"armRight"},{"length":27.3,"transform":{"skX":-82.4879,"y":-21.3,"skY":-82.4879,"x":11.1},"parent":"root","name":"eyeRight"},{"length":18.3,"transform":{"skX":140.9061,"y":18.9,"skY":140.9061,"x":-9.9},"parent":"root","name":"leg2"},{"length":20.7,"transform":{"skX":45,"y":16.5,"skY":45,"x":9.6},"parent":"root","name":"leg3"},{"length":19.5,"transform":{"skX":55.5816,"y":10.799999999999999,"skY":55.5816,"x":32.4},"parent":"root","name":"leg4"},{"length":32.1,"transform":{"skX":12.7089,"y":-0.29274,"skY":12.7089,"x":30.53529},"parent":"armLeft","name":"handLeft"},{"length":35.1,"transform":{"skX":-14.0755,"y":1.57191,"skY":-14.0755,"x":27.69204},"parent":"armRight","name":"handRight"},{"length":26.7,"transform":{"skX":36.941,"y":0.26217,"skY":36.941,"x":2.45994},"parent":"handLeft","name":"clawLeft"},{"length":25.8,"transform":{"skX":-36.2054,"y":-2.87775,"skY":-36.2054,"x":4.02474},"parent":"handRight","name":"clawRight"}],"ik":[],"aabb":{"width":368,"y":-189.6159420289855,"height":336.5,"x":-181.5},"name":"Crab","slot":[{"name":"body","parent":"root","color":{}},{"z":1,"name":"armLeft","parent":"armLeft","color":{}},{"z":2,"name":"armRight","parent":"armRight","color":{}},{"z":3,"name":"clawLeft","parent":"clawLeft","color":{}},{"z":4,"name":"clawRight","parent":"clawRight","color":{}},{"z":5,"name":"eyeLeft","parent":"eyeLeft","color":{}},{"z":6,"name":"eyeRight","parent":"eyeRight","color":{}},{"z":7,"name":"handLeft","parent":"handLeft","color":{}},{"z":8,"name":"handRight","parent":"handRight","color":{}},{"z":9,"name":"leg1","parent":"leg1","color":{}},{"z":10,"name":"leg2","parent":"leg2","color":{}},{"z":11,"name":"leg3","parent":"leg3","color":{}},{"z":12,"name":"leg4","parent":"leg4","color":{}}]}],"name":"Crab","version":"4.5"}